{
  "cookies": [
    {
      "name": "wordpress_sec_bcee46caf8128c4169fb42a56c1b36e7",
      "value": "practiceuser1%7C1693859690%7CPry2YyjYUh5ALmNnIXQL3n0e0x1czRI0KWjmXnrXjGh%7C147c6ece471ffff1606febe1477665d6d06ed93b85674d45df5fcc495a7ed48d",
      "domain": "practice.sdetunicorns.com",
      "path": "/wp-content/plugins",
      "expires": -1,
      "httpOnly": true,
      "secure": true,
      "sameSite": "None"
    },
    {
      "name": "wordpress_sec_bcee46caf8128c4169fb42a56c1b36e7",
      "value": "practiceuser1%7C1693859690%7CPry2YyjYUh5ALmNnIXQL3n0e0x1czRI0KWjmXnrXjGh%7C147c6ece471ffff1606febe1477665d6d06ed93b85674d45df5fcc495a7ed48d",
      "domain": "practice.sdetunicorns.com",
      "path": "/wp-admin",
      "expires": -1,
      "httpOnly": true,
      "secure": true,
      "sameSite": "None"
    },
    {
      "name": "wp_wpfileupload_e07ef222fe18f1b43430eb5704226509",
      "value": "CNQRm5nnmrznPM43wcZaZyOedkkKmpLy",
      "domain": "practice.automationbro.com",
      "path": "/",
      "expires": 1693859685.632572,
      "httpOnly": false,
      "secure": false,
      "sameSite": "Lax"
    },
    {
      "name": "wp_wpfileupload_bcee46caf8128c4169fb42a56c1b36e7",
      "value": "rkOBY26kYxXO86K8GCdm6bGXzxRYe1me",
      "domain": "practice.sdetunicorns.com",
      "path": "/",
      "expires": 1693859686.553007,
      "httpOnly": false,
      "secure": false,
      "sameSite": "Lax"
    },
    {
      "name": "tk_or",
      "value": "%22%22",
      "domain": ".sdetunicorns.com",
      "path": "/",
      "expires": 1728246889.011939,
      "httpOnly": false,
      "secure": false,
      "sameSite": "Lax"
    },
    {
      "name": "tk_r3d",
      "value": "%22%22",
      "domain": ".sdetunicorns.com",
      "path": "/",
      "expires": 1693946089,
      "httpOnly": false,
      "secure": false,
      "sameSite": "Lax"
    },
    {
      "name": "tk_lr",
      "value": "%22%22",
      "domain": ".sdetunicorns.com",
      "path": "/",
      "expires": 1725222889,
      "httpOnly": false,
      "secure": false,
      "sameSite": "Lax"
    },
    {
      "name": "wordpress_logged_in_bcee46caf8128c4169fb42a56c1b36e7",
      "value": "practiceuser1%7C1693859690%7CPry2YyjYUh5ALmNnIXQL3n0e0x1czRI0KWjmXnrXjGh%7C8c86df67db0e76768b9150676d56cda144faba4c6e97bbbaf5abd3c5eb3db9f1",
      "domain": "practice.sdetunicorns.com",
      "path": "/",
      "expires": -1,
      "httpOnly": true,
      "secure": false,
      "sameSite": "Lax"
    },
    {
      "name": "woocommerce_items_in_cart",
      "value": "1",
      "domain": "practice.sdetunicorns.com",
      "path": "/",
      "expires": -1,
      "httpOnly": false,
      "secure": false,
      "sameSite": "Lax"
    },
    {
      "name": "woocommerce_cart_hash",
      "value": "6b4f5128aced7ce3ea1d0fab860bc584",
      "domain": "practice.sdetunicorns.com",
      "path": "/",
      "expires": -1,
      "httpOnly": false,
      "secure": false,
      "sameSite": "Lax"
    },
    {
      "name": "wp_woocommerce_session_bcee46caf8128c4169fb42a56c1b36e7",
      "value": "175%7C%7C1693859691%7C%7C1693856091%7C%7C613b86025229f277d7b64193b8f9cc7f",
      "domain": "practice.sdetunicorns.com",
      "path": "/",
      "expires": 1693859691.869726,
      "httpOnly": true,
      "secure": false,
      "sameSite": "Lax"
    }
  ],
  "origins": []
}